apimaticcalculator/__init__.py
apimaticcalculator/api_helper.py
apimaticcalculator/apimaticcalculator_client.py
apimaticcalculator/configuration.py
apimaticcalculator/controllers/__init__.py
apimaticcalculator/controllers/base_controller.py
apimaticcalculator/controllers/simple_calculator_controller.py
apimaticcalculator/exceptions/__init__.py
apimaticcalculator/exceptions/api_exception.py
apimaticcalculator/http/__init__.py
apimaticcalculator/http/http_call_back.py
apimaticcalculator/http/http_method_enum.py
apimaticcalculator/http/http_request.py
apimaticcalculator/http/http_response.py
apimaticcalculator/models/__init__.py
apimaticcalculator/models/operation_type_enum.py
apimaticcalculator/utilities/__init__.py
apimaticcalculator/utilities/file_wrapper.py
myUniquePythonPackageName-100.0.100.dist-info/LICENSE
myUniquePythonPackageName-100.0.100.dist-info/METADATA
myUniquePythonPackageName-100.0.100.dist-info/WHEEL
myUniquePythonPackageName-100.0.100.dist-info/top_level.txt
myUniquePythonPackageName-100.0.100.dist-info/RECORD
